hogben/README.md
hogben/__init__.py
hogben/angles.py
hogben/contrasts.py
hogben/kinetics.py
hogben/magnetism.py
hogben/optimise.py
hogben/simulate.py
hogben/underlayers.py
hogben/utils.py
hogben/visualise.py
hogben/data/__init__.py
hogben/data/DMPC_bilayer/Si-D2O.dat
hogben/data/DMPC_bilayer/Si-DMPC-D2O.dat
hogben/data/DMPC_bilayer/Si-DMPC-H2O.dat
hogben/data/DPPC_RaLPS_bilayer/dDPPC-RaLPS-D2O.dat
hogben/data/DPPC_RaLPS_bilayer/dDPPC-RaLPS-H2O.dat
hogben/data/DPPC_RaLPS_bilayer/dDPPC-RaLPS-SMW.dat
hogben/data/DPPG_monolayer/dDPPG-NRW.dat
hogben/data/DPPG_monolayer/hDPPG-D2O.dat
hogben/data/DPPG_monolayer/hDPPG-NRW.dat
hogben/data/YIG_sample/YIG_down.dat
hogben/data/YIG_sample/YIG_up.dat
hogben/data/directbeams/INTER_non_polarised.dat
hogben/data/directbeams/OFFSPEC_Polarised.dat
hogben/data/directbeams/OFFSPEC_non_polarised.dat
hogben/data/directbeams/OFFSPEC_non_polarised_old.dat
hogben/data/directbeams/OFFSPEC_polarised_old.dat
hogben/data/directbeams/POLREF_non_polarised.dat
hogben/data/directbeams/POLREF_polarised.dat
hogben/data/directbeams/SURF_non_polarised.dat
hogben/data/directbeams/__init__.py
hogben/data/directbeams/make_beam_spectra.py
hogben/models/README.md
hogben/models/__init__.py
hogben/models/base.py
hogben/models/bilayers.py
hogben/models/magnetic.py
hogben/models/monolayers.py
hogben/models/parsing.py
hogben/models/samples.py
hogben/tests/__init__.py
hogben/tests/test_fisher.py
hogben/tests/test_optimise.py
hogben/tests/test_samples.py
hogben/tests/test_simulation.py
hogben/tests/test_visualise.py
HOGBEN-3.1.1.dist-info/LICENSE
HOGBEN-3.1.1.dist-info/METADATA
HOGBEN-3.1.1.dist-info/WHEEL
HOGBEN-3.1.1.dist-info/top_level.txt
HOGBEN-3.1.1.dist-info/RECORD
