Metadata-Version: 2.1
Name: HOGBEN
Version: 3.1.1
Summary: Holistic Optimization for Generating Better Experimental Neutrons - a package for optimzing neutron experiments using the Fisher information
Home-page: https://github.com/jfkcooper/HOGBEN
Author: Joshaniel Cooper
Author-email: Jos.Cooper@stfc.ac.uk
Project-URL: Bug Tracker, https://github.com/jfkcooper/HOGBEN/issues
Classifier: Programming Language :: Python :: 3
Classifier: License :: OSI Approved :: BSD License
Classifier: Operating System :: OS Independent
Classifier: Topic :: Scientific/Engineering :: Artificial Intelligence
Requires-Python: >=3.10
License-File: LICENSE
Requires-Dist: bumps
Requires-Dist: corner
Requires-Dist: dynesty
Requires-Dist: emcee
Requires-Dist: importlib-resources
Requires-Dist: matplotlib
Requires-Dist: numpy
Requires-Dist: periodictable
Requires-Dist: Pillow
Requires-Dist: refl1d
Requires-Dist: refnx
Requires-Dist: tqdm
Requires-Dist: scipy
